{"blocks":{"0d57e9ff64952_1606854334045":{"id":"0d57e9ff64952_1606854334045","x":23,"y":10,"anchorPoint":{"x":0,"y":0},"pixels":{"0,0":{"x":0,"y":0,"color":"gray","clearEdges":["top","left"]},"1,0":{"x":1,"y":0,"color":"gray","clearEdges":["top"]},"2,0":{"x":2,"y":0,"color":"gray","clearEdges":["top"]},"3,0":{"x":3,"y":0,"color":"gray","clearEdges":["top","right"]},"0,1":{"x":0,"y":1,"color":"gray","clearEdges":["bottom","left"]},"1,1":{"x":1,"y":1,"color":"gray","clearEdges":["bottom"]},"2,1":{"x":2,"y":1,"color":"gray","clearEdges":["bottom"]},"3,1":{"x":3,"y":1,"color":"gray","clearEdges":["bottom","right"]}}},"9ff008da856a3_1606854349928":{"id":"9ff008da856a3_1606854349928","x":21,"y":12,"anchorPoint":{"x":0,"y":0},"pixels":{"0,0":{"x":0,"y":0,"color":"gray","clearEdges":["top","left"]},"1,0":{"x":1,"y":0,"color":"gray","clearEdges":["top"]},"2,0":{"x":2,"y":0,"color":"gray","clearEdges":["top"]},"3,0":{"x":3,"y":0,"color":"gray","clearEdges":["top","right"]},"0,1":{"x":0,"y":1,"color":"gray","clearEdges":["bottom","left"]},"1,1":{"x":1,"y":1,"color":"gray","clearEdges":["bottom"]},"2,1":{"x":2,"y":1,"color":"gray","clearEdges":["bottom"]},"3,1":{"x":3,"y":1,"color":"gray","clearEdges":["bottom","right"]}}},"ea2f3de104425_1606854357775":{"id":"ea2f3de104425_1606854357775","x":25,"y":12,"anchorPoint":{"x":0,"y":0},"pixels":{"0,0":{"x":0,"y":0,"color":"gray","clearEdges":["top","left"]},"1,0":{"x":1,"y":0,"color":"gray","clearEdges":["top"]},"2,0":{"x":2,"y":0,"color":"gray","clearEdges":["top"]},"3,0":{"x":3,"y":0,"color":"gray","clearEdges":["top","right"]},"0,1":{"x":0,"y":1,"color":"gray","clearEdges":["bottom","left"]},"1,1":{"x":1,"y":1,"color":"gray","clearEdges":["bottom"]},"2,1":{"x":2,"y":1,"color":"gray","clearEdges":["bottom"]},"3,1":{"x":3,"y":1,"color":"gray","clearEdges":["bottom","right"]}}},"cd28b4cd44e8f_1606854368309":{"id":"cd28b4cd44e8f_1606854368309","x":23,"y":14,"anchorPoint":{"x":0,"y":0},"pixels":{"0,0":{"x":0,"y":0,"color":"gray","clearEdges":["top","left"]},"1,0":{"x":1,"y":0,"color":"gray","clearEdges":["top"]},"2,0":{"x":2,"y":0,"color":"gray","clearEdges":["top"]},"3,0":{"x":3,"y":0,"color":"gray","clearEdges":["top","right"]},"0,1":{"x":0,"y":1,"color":"gray","clearEdges":["bottom","left"]},"1,1":{"x":1,"y":1,"color":"gray","clearEdges":["bottom"]},"2,1":{"x":2,"y":1,"color":"gray","clearEdges":["bottom"]},"3,1":{"x":3,"y":1,"color":"gray","clearEdges":["bottom","right"]}}},"3b3c4793bc08a_1606906468568":{"id":"3b3c4793bc08a_1606906468568","x":16,"y":5,"anchorPoint":{"x":0,"y":0},"pixels":{"0,0":{"x":0,"y":0,"color":"gray","clearEdges":["top","left"]},"1,0":{"x":1,"y":0,"color":"gray","clearEdges":["top"]},"2,0":{"x":2,"y":0,"color":"gray","clearEdges":["top"]},"3,0":{"x":3,"y":0,"color":"gray","clearEdges":["top","right"]},"0,1":{"x":0,"y":1,"color":"gray","clearEdges":["bottom","left"]},"1,1":{"x":1,"y":1,"color":"gray","clearEdges":["bottom"]},"2,1":{"x":2,"y":1,"color":"gray","clearEdges":["bottom"]},"3,1":{"x":3,"y":1,"color":"gray","clearEdges":["bottom","right"]}}},"c03fd8154eadf_1606906468898":{"id":"c03fd8154eadf_1606906468898","x":21,"y":5,"anchorPoint":{"x":0,"y":0},"pixels":{"0,0":{"x":0,"y":0,"color":"gray","clearEdges":["top","left"]},"1,0":{"x":1,"y":0,"color":"gray","clearEdges":["top"]},"2,0":{"x":2,"y":0,"color":"gray","clearEdges":["top"]},"3,0":{"x":3,"y":0,"color":"gray","clearEdges":["top","right"]},"0,1":{"x":0,"y":1,"color":"gray","clearEdges":["bottom","left"]},"1,1":{"x":1,"y":1,"color":"gray","clearEdges":["bottom"]},"2,1":{"x":2,"y":1,"color":"gray","clearEdges":["bottom"]},"3,1":{"x":3,"y":1,"color":"gray","clearEdges":["bottom","right"]}}},"442244eb72501_1606906469247":{"id":"442244eb72501_1606906469247","x":26,"y":5,"anchorPoint":{"x":0,"y":0},"pixels":{"0,0":{"x":0,"y":0,"color":"gray","clearEdges":["top","left"]},"1,0":{"x":1,"y":0,"color":"gray","clearEdges":["top"]},"2,0":{"x":2,"y":0,"color":"gray","clearEdges":["top"]},"3,0":{"x":3,"y":0,"color":"gray","clearEdges":["top","right"]},"0,1":{"x":0,"y":1,"color":"gray","clearEdges":["bottom","left"]},"1,1":{"x":1,"y":1,"color":"gray","clearEdges":["bottom"]},"2,1":{"x":2,"y":1,"color":"gray","clearEdges":["bottom"]},"3,1":{"x":3,"y":1,"color":"gray","clearEdges":["bottom","right"]}}},"fb8810ff2b9c3_1606906469697":{"id":"fb8810ff2b9c3_1606906469697","x":32,"y":5,"anchorPoint":{"x":0,"y":0},"pixels":{"0,0":{"x":0,"y":0,"color":"gray","clearEdges":["top","left"]},"1,0":{"x":1,"y":0,"color":"gray","clearEdges":["top"]},"2,0":{"x":2,"y":0,"color":"gray","clearEdges":["top"]},"3,0":{"x":3,"y":0,"color":"gray","clearEdges":["top","right"]},"0,1":{"x":0,"y":1,"color":"gray","clearEdges":["bottom","left"]},"1,1":{"x":1,"y":1,"color":"gray","clearEdges":["bottom"]},"2,1":{"x":2,"y":1,"color":"gray","clearEdges":["bottom"]},"3,1":{"x":3,"y":1,"color":"gray","clearEdges":["bottom","right"]}}},"4b7c5d3956d33_1606919326505":{"id":"4b7c5d3956d33_1606919326505","x":8,"y":21,"anchorPoint":{"x":0,"y":0},"pixels":{"0,0":{"x":0,"y":0,"color":"gray","clearEdges":["top","left"]},"1,0":{"x":1,"y":0,"color":"gray","clearEdges":["top"]},"2,0":{"x":2,"y":0,"color":"gray","clearEdges":["top"]},"3,0":{"x":3,"y":0,"color":"gray","clearEdges":["top","right"]},"0,1":{"x":0,"y":1,"color":"gray","clearEdges":["bottom","left"]},"1,1":{"x":1,"y":1,"color":"gray","clearEdges":["bottom"]},"2,1":{"x":2,"y":1,"color":"gray","clearEdges":["bottom"]},"3,1":{"x":3,"y":1,"color":"gray","clearEdges":["bottom","right"]}}},"5c637caf83554_1606919327663":{"id":"5c637caf83554_1606919327663","x":17,"y":21,"anchorPoint":{"x":0,"y":0},"pixels":{"0,0":{"x":0,"y":0,"color":"gray","clearEdges":["top","left"]},"1,0":{"x":1,"y":0,"color":"gray","clearEdges":["top"]},"2,0":{"x":2,"y":0,"color":"gray","clearEdges":["top"]},"3,0":{"x":3,"y":0,"color":"gray","clearEdges":["top","right"]},"0,1":{"x":0,"y":1,"color":"gray","clearEdges":["bottom","left"]},"1,1":{"x":1,"y":1,"color":"gray","clearEdges":["bottom"]},"2,1":{"x":2,"y":1,"color":"gray","clearEdges":["bottom"]},"3,1":{"x":3,"y":1,"color":"gray","clearEdges":["bottom","right"]}}},"8c59c5368dde7_1606919328830":{"id":"8c59c5368dde7_1606919328830","x":27,"y":21,"anchorPoint":{"x":0,"y":0},"pixels":{"0,0":{"x":0,"y":0,"color":"gray","clearEdges":["top","left"]},"1,0":{"x":1,"y":0,"color":"gray","clearEdges":["top"]},"2,0":{"x":2,"y":0,"color":"gray","clearEdges":["top"]},"3,0":{"x":3,"y":0,"color":"gray","clearEdges":["top","right"]},"0,1":{"x":0,"y":1,"color":"gray","clearEdges":["bottom","left"]},"1,1":{"x":1,"y":1,"color":"gray","clearEdges":["bottom"]},"2,1":{"x":2,"y":1,"color":"gray","clearEdges":["bottom"]},"3,1":{"x":3,"y":1,"color":"gray","clearEdges":["bottom","right"]}}},"a57a3d2d2c812_1606920753581":{"id":"a57a3d2d2c812_1606920753581","x":8,"y":18,"anchorPoint":{"x":0,"y":0},"pixels":{"0,0":{"x":0,"y":0,"color":"gray","clearEdges":["top","left"]},"1,0":{"x":1,"y":0,"color":"gray","clearEdges":["top"]},"2,0":{"x":2,"y":0,"color":"gray","clearEdges":["top"]},"3,0":{"x":3,"y":0,"color":"gray","clearEdges":["top","right"]},"0,1":{"x":0,"y":1,"color":"gray","clearEdges":["bottom","left"]},"1,1":{"x":1,"y":1,"color":"gray","clearEdges":["bottom"]},"2,1":{"x":2,"y":1,"color":"gray","clearEdges":["bottom"]},"3,1":{"x":3,"y":1,"color":"gray","clearEdges":["bottom","right"]}}},"675dbd2bb0bbf_1606920753582":{"id":"675dbd2bb0bbf_1606920753582","x":17,"y":18,"anchorPoint":{"x":0,"y":0},"pixels":{"0,0":{"x":0,"y":0,"color":"gray","clearEdges":["top","left"]},"1,0":{"x":1,"y":0,"color":"gray","clearEdges":["top"]},"2,0":{"x":2,"y":0,"color":"gray","clearEdges":["top"]},"3,0":{"x":3,"y":0,"color":"gray","clearEdges":["top","right"]},"0,1":{"x":0,"y":1,"color":"gray","clearEdges":["bottom","left"]},"1,1":{"x":1,"y":1,"color":"gray","clearEdges":["bottom"]},"2,1":{"x":2,"y":1,"color":"gray","clearEdges":["bottom"]},"3,1":{"x":3,"y":1,"color":"gray","clearEdges":["bottom","right"]}}},"b40ec8ec5253c_1606920753583":{"id":"b40ec8ec5253c_1606920753583","x":27,"y":18,"anchorPoint":{"x":0,"y":0},"pixels":{"0,0":{"x":0,"y":0,"color":"gray","clearEdges":["top","left"]},"1,0":{"x":1,"y":0,"color":"gray","clearEdges":["top"]},"2,0":{"x":2,"y":0,"color":"gray","clearEdges":["top"]},"3,0":{"x":3,"y":0,"color":"gray","clearEdges":["top","right"]},"0,1":{"x":0,"y":1,"color":"gray","clearEdges":["bottom","left"]},"1,1":{"x":1,"y":1,"color":"gray","clearEdges":["bottom"]},"2,1":{"x":2,"y":1,"color":"gray","clearEdges":["bottom"]},"3,1":{"x":3,"y":1,"color":"gray","clearEdges":["bottom","right"]}}}},"gridPoints":{"23,10":"0d57e9ff64952_1606854334045","24,10":"0d57e9ff64952_1606854334045","25,10":"0d57e9ff64952_1606854334045","26,10":"0d57e9ff64952_1606854334045","23,11":"0d57e9ff64952_1606854334045","24,11":"0d57e9ff64952_1606854334045","25,11":"0d57e9ff64952_1606854334045","26,11":"0d57e9ff64952_1606854334045","21,12":"9ff008da856a3_1606854349928","22,12":"9ff008da856a3_1606854349928","23,12":"9ff008da856a3_1606854349928","24,12":"9ff008da856a3_1606854349928","21,13":"9ff008da856a3_1606854349928","22,13":"9ff008da856a3_1606854349928","23,13":"9ff008da856a3_1606854349928","24,13":"9ff008da856a3_1606854349928","25,12":"ea2f3de104425_1606854357775","26,12":"ea2f3de104425_1606854357775","27,12":"ea2f3de104425_1606854357775","28,12":"ea2f3de104425_1606854357775","25,13":"ea2f3de104425_1606854357775","26,13":"ea2f3de104425_1606854357775","27,13":"ea2f3de104425_1606854357775","28,13":"ea2f3de104425_1606854357775","23,14":"cd28b4cd44e8f_1606854368309","24,14":"cd28b4cd44e8f_1606854368309","25,14":"cd28b4cd44e8f_1606854368309","26,14":"cd28b4cd44e8f_1606854368309","23,15":"cd28b4cd44e8f_1606854368309","24,15":"cd28b4cd44e8f_1606854368309","25,15":"cd28b4cd44e8f_1606854368309","26,15":"cd28b4cd44e8f_1606854368309","21,5":"c03fd8154eadf_1606906468898","22,5":"c03fd8154eadf_1606906468898","23,5":"c03fd8154eadf_1606906468898","24,5":"c03fd8154eadf_1606906468898","21,6":"c03fd8154eadf_1606906468898","22,6":"c03fd8154eadf_1606906468898","23,6":"c03fd8154eadf_1606906468898","24,6":"c03fd8154eadf_1606906468898","32,5":"fb8810ff2b9c3_1606906469697","33,5":"fb8810ff2b9c3_1606906469697","34,5":"fb8810ff2b9c3_1606906469697","35,5":"fb8810ff2b9c3_1606906469697","32,6":"fb8810ff2b9c3_1606906469697","33,6":"fb8810ff2b9c3_1606906469697","34,6":"fb8810ff2b9c3_1606906469697","35,6":"fb8810ff2b9c3_1606906469697","26,5":"442244eb72501_1606906469247","27,5":"442244eb72501_1606906469247","28,5":"442244eb72501_1606906469247","29,5":"442244eb72501_1606906469247","26,6":"442244eb72501_1606906469247","27,6":"442244eb72501_1606906469247","28,6":"442244eb72501_1606906469247","29,6":"442244eb72501_1606906469247","16,5":"3b3c4793bc08a_1606906468568","17,5":"3b3c4793bc08a_1606906468568","18,5":"3b3c4793bc08a_1606906468568","19,5":"3b3c4793bc08a_1606906468568","16,6":"3b3c4793bc08a_1606906468568","17,6":"3b3c4793bc08a_1606906468568","18,6":"3b3c4793bc08a_1606906468568","19,6":"3b3c4793bc08a_1606906468568","8,21":"4b7c5d3956d33_1606919326505","9,21":"4b7c5d3956d33_1606919326505","10,21":"4b7c5d3956d33_1606919326505","11,21":"4b7c5d3956d33_1606919326505","8,22":"4b7c5d3956d33_1606919326505","9,22":"4b7c5d3956d33_1606919326505","10,22":"4b7c5d3956d33_1606919326505","11,22":"4b7c5d3956d33_1606919326505","17,21":"5c637caf83554_1606919327663","18,21":"5c637caf83554_1606919327663","19,21":"5c637caf83554_1606919327663","20,21":"5c637caf83554_1606919327663","17,22":"5c637caf83554_1606919327663","18,22":"5c637caf83554_1606919327663","19,22":"5c637caf83554_1606919327663","20,22":"5c637caf83554_1606919327663","27,21":"8c59c5368dde7_1606919328830","28,21":"8c59c5368dde7_1606919328830","29,21":"8c59c5368dde7_1606919328830","30,21":"8c59c5368dde7_1606919328830","27,22":"8c59c5368dde7_1606919328830","28,22":"8c59c5368dde7_1606919328830","29,22":"8c59c5368dde7_1606919328830","30,22":"8c59c5368dde7_1606919328830","8,18":"a57a3d2d2c812_1606920753581","9,18":"a57a3d2d2c812_1606920753581","10,18":"a57a3d2d2c812_1606920753581","11,18":"a57a3d2d2c812_1606920753581","8,19":"a57a3d2d2c812_1606920753581","9,19":"a57a3d2d2c812_1606920753581","10,19":"a57a3d2d2c812_1606920753581","11,19":"a57a3d2d2c812_1606920753581","17,18":"675dbd2bb0bbf_1606920753582","18,18":"675dbd2bb0bbf_1606920753582","19,18":"675dbd2bb0bbf_1606920753582","20,18":"675dbd2bb0bbf_1606920753582","17,19":"675dbd2bb0bbf_1606920753582","18,19":"675dbd2bb0bbf_1606920753582","19,19":"675dbd2bb0bbf_1606920753582","20,19":"675dbd2bb0bbf_1606920753582","27,18":"b40ec8ec5253c_1606920753583","28,18":"b40ec8ec5253c_1606920753583","29,18":"b40ec8ec5253c_1606920753583","30,18":"b40ec8ec5253c_1606920753583","27,19":"b40ec8ec5253c_1606920753583","28,19":"b40ec8ec5253c_1606920753583","29,19":"b40ec8ec5253c_1606920753583","30,19":"b40ec8ec5253c_1606920753583"}}